mini_bash.py
mini_bash-0.1.1.dist-info/LICENSE
mini_bash-0.1.1.dist-info/METADATA
mini_bash-0.1.1.dist-info/WHEEL
mini_bash-0.1.1.dist-info/RECORD
