Metadata-Version: 2.1
Name: mini_bash
Version: 0.1.1
Summary: Easily run bash commands
Home-page: https://github.com/lamnguyenx/mini_bash.git
License: apache
Author: lamnguyenx
Author-email: lamfm95@gmail.com
Requires-Python: >=3.7,<4.0
Classifier: License :: Other/Proprietary License
Classifier: Programming Language :: Python :: 3
Classifier: Programming Language :: Python :: 3.7
Classifier: Programming Language :: Python :: 3.8
Classifier: Programming Language :: Python :: 3.9
Classifier: Programming Language :: Python :: 3.10
Classifier: Programming Language :: Python :: 3.11
Classifier: Programming Language :: Python :: 3.12
Classifier: Programming Language :: Python :: 3.13
